MANIFEST.in
README.md
setup.py
synergine_lifegame/PlotTerminal.py
synergine_lifegame/PrintTerminal.py
synergine_lifegame/__init__.py
synergine_lifegame/cst.py
synergine_lifegame.egg-info/PKG-INFO
synergine_lifegame.egg-info/SOURCES.txt
synergine_lifegame.egg-info/dependency_links.txt
synergine_lifegame.egg-info/requires.txt
synergine_lifegame.egg-info/top_level.txt
synergine_lifegame/curses/__init__.py
synergine_lifegame/display/__init__.py
synergine_lifegame/display/curses_visualisation.py
synergine_lifegame/display/pygame_visualisation.py
synergine_lifegame/display/pygame/__init__.py
synergine_lifegame/display/pygame/cha.png
synergine_lifegame/display/pygame/cha0.png
synergine_lifegame/display/pygame/cha2.png
synergine_lifegame/display/pygame/cha3.png
synergine_lifegame/display/pygame/debug.png
synergine_lifegame/synergy/LifeGameSimulation.py
synergine_lifegame/synergy/__init__.py
synergine_lifegame/synergy/collection/LifeGameCollection.py
synergine_lifegame/synergy/collection/LifeGameCollectionConfiguration.py
synergine_lifegame/synergy/collection/__init__.py
synergine_lifegame/synergy/event/AliveAroundEvent.py
synergine_lifegame/synergy/event/BornAction.py
synergine_lifegame/synergy/event/DieAction.py
synergine_lifegame/synergy/event/GoodConditionToBornEvent.py
synergine_lifegame/synergy/event/NotGoodConditionToPersistEvent.py
synergine_lifegame/synergy/event/TimePassAction.py
synergine_lifegame/synergy/event/TimePassEvent.py
synergine_lifegame/synergy/event/__init__.py
synergine_lifegame/synergy/object/Cell.py
synergine_lifegame/synergy/object/__init__.py